dj_twiml/__init__.py
dj_twiml/admin.py
dj_twiml/models.py
dj_twiml/urls.py
dj_twiml/views.py
dj_twiml/migrations/0001_initial.py
dj_twiml/migrations/__init__.py
dj_twiml/south_migrations/0001_initial.py
dj_twiml/south_migrations/__init__.py
dj_twiml-0.1.3.dist-info/DESCRIPTION.rst
dj_twiml-0.1.3.dist-info/METADATA
dj_twiml-0.1.3.dist-info/pydist.json
dj_twiml-0.1.3.dist-info/RECORD
dj_twiml-0.1.3.dist-info/top_level.txt
dj_twiml-0.1.3.dist-info/WHEEL
