Metadata-Version: 2.0
Name: dj-twiml
Version: 0.1.3
Summary: Create Twilio TwiML views in Django
Home-page: https://github.com/phalt/dj-twiml
Author: Paul Hallett
Author-email: paul@twilio.com
License: BSD
Keywords: django,twilio,twiml,telephony
Platform: UNKNOWN
Classifier: Development Status :: 4 - Beta
Classifier: Framework :: Django
Classifier: Intended Audience :: Developers
Classifier: License :: OSI Approved :: BSD License
Classifier: Natural Language :: English
Classifier: Programming Language :: Python :: 2
Classifier: Programming Language :: Python :: 2.6
Classifier: Programming Language :: Python :: 2.7
Requires-Dist: django-twilio
